{
  "stocks": [
    {
      "ticker": "RAIZ4 RAIZEN S.A.",
      "companyName": "RAIZEN S.A.",
      "variation": "2,28"
    },
    {
      "ticker": "EMBR3 EMBRAER",
      "companyName": "EMBRAER",
      "variation": "1,60"
    },
    {
      "ticker": "TIMS3 TIM",
      "companyName": "TIM",
      "variation": "1,30"
    },
    {
      "ticker": "VBBR3 VIBRA ENERGIA S.A.",
      "companyName": "VIBRA ENERGIA S.A.",
      "variation": "1,14"
    },
    {
      "ticker": "EGIE3 ENGIE BRASIL",
      "companyName": "ENGIE BRASIL",
      "variation": "0,58"
    },
    {
      "ticker": "PRIO3 PETRO RIO",
      "companyName": "PETRO RIO",
      "variation": "0,43"
    }
  ]
}
